[{"organizador":"Alemania","selecciones":32,"partidos":64,"goles":147,"promedio_gol":2.30,"año":2006},
{"organizador":"Suiza","selecciones":16,"partidos":26,"goles":140,"promedio_gol":5.38,"año":1954},
{"organizador":"Suecia","selecciones":16,"partidos":35,"goles":126,"promedio_gol":3.60,"año":1958},
{"organizador":"Rusia","selecciones":32,"partidos":64,"goles":169,"promedio_gol":2.64,"año":2018},
{"organizador":"Italia","selecciones":16,"partidos":17,"goles":70,"promedio_gol":4.12,"año":1934},
{"organizador":"Uruguay","selecciones":13,"partidos":18,"goles":70,"promedio_gol":3.89,"año":1930},
{"organizador":"Brasil","selecciones":32,"partidos":64,"goles":171,"promedio_gol":2.67,"año":2014},
{"organizador":"Francia","selecciones":16,"partidos":18,"goles":84,"promedio_gol":4.67,"año":1938},
{"organizador":"Sudáfrica","selecciones":32,"partidos":64,"goles":145,"promedio_gol":2.27,"año":2010},
{"organizador":"Brasil","selecciones":13,"partidos":22,"goles":88,"promedio_gol":4.00,"año":1950},
{"organizador":"Chile","selecciones":16,"partidos":32,"goles":89,"promedio_gol":2.78,"año":1962},
{"organizador":"Alemania Occidental","selecciones":16,"partidos":38,"goles":97,"promedio_gol":2.55,"año":1974},
{"organizador":"Inglaterra","selecciones":16,"partidos":32,"goles":89,"promedio_gol":2.78,"año":1966},
{"organizador":"Argentina","selecciones":16,"partidos":38,"goles":102,"promedio_gol":2.68,"año":1978},
{"organizador":"México","selecciones":16,"partidos":32,"goles":95,"promedio_gol":2.97,"año":1970},
{"organizador":"España","selecciones":24,"partidos":52,"goles":146,"promedio_gol":2.81,"año":1982},
{"organizador":"Italia","selecciones":24,"partidos":52,"goles":115,"promedio_gol":2.21,"año":1990},
{"organizador":"México","selecciones":24,"partidos":52,"goles":132,"promedio_gol":2.54,"año":1986},
{"organizador":"Estados Unidos","selecciones":24,"partidos":52,"goles":141,"promedio_gol":2.71,"año":1994},
{"organizador":"Francia","selecciones":32,"partidos":64,"goles":171,"promedio_gol":2.67,"año":1998},
{"organizador":"Corea / Japón","selecciones":32,"partidos":64,"goles":161,"promedio_gol":2.52,"año":2002}
]
